MetricDB/__init__.py
MetricDB/src/__init__.py
MetricDB/src/main.py
MetricDB-0.0.13.dist-info/LICENSE
MetricDB-0.0.13.dist-info/METADATA
MetricDB-0.0.13.dist-info/WHEEL
MetricDB-0.0.13.dist-info/top_level.txt
MetricDB-0.0.13.dist-info/RECORD
