Metadata-Version: 2.1
Name: MetricDB
Version: 0.0.13
Summary: A logger based on SQLite3
Home-page: https://github.com/Don-Yin/MetricDB
Author: Don Yin
Author-email: Don_Yin@outlook.com
Classifier: Programming Language :: Python :: 3
Classifier: License :: OSI Approved :: MIT License
Classifier: Operating System :: OS Independent
Requires-Python: >=3.11
License-File: LICENSE
